engineering_memory_bank-0.0.1.dist-info/licenses/LICENSE
memory_bank/__init__.py
memory_bank/ai/analyzer.py
memory_bank/core/decision.py
memory_bank/core/memory_bank.py
memory_bank/git/integration.py
memory_bank/mcp/server.py
memory_bank/utils/exceptions.py
engineering_memory_bank-0.0.1.dist-info/METADATA
engineering_memory_bank-0.0.1.dist-info/WHEEL
engineering_memory_bank-0.0.1.dist-info/entry_points.txt
engineering_memory_bank-0.0.1.dist-info/top_level.txt
engineering_memory_bank-0.0.1.dist-info/RECORD
