Metadata-Version: 2.4
Name: engineering-memory-bank
Version: 0.0.1
Summary: AI-powered engineering decision documentation system with automatic git integration
Author-email: Circuit-Synth <info@circuit-synth.com>
Maintainer-email: Circuit-Synth <info@circuit-synth.com>
License-Expression: MIT
Project-URL: Homepage, https://github.com/circuit-synth/engineering-memory-bank
Project-URL: Documentation, https://circuit-synth.github.io/engineering-memory-bank/
Project-URL: Repository, https://github.com/circuit-synth/engineering-memory-bank.git
Project-URL: Bug Reports, https://github.com/circuit-synth/engineering-memory-bank/issues
Project-URL: Changelog, https://github.com/circuit-synth/engineering-memory-bank/blob/main/CHANGELOG.md
Keywords: engineering,documentation,ai,git,decisions,knowledge-management,automation,mcp,claude
Classifier: Development Status :: 3 - Alpha
Classifier: Intended Audience :: Developers
Classifier: Intended Audience :: Science/Research
Classifier: Topic :: Software Development :: Documentation
Classifier: Topic :: Scientific/Engineering
Classifier: Topic :: Text Processing :: Markup :: Markdown
Classifier: Programming Language :: Python :: 3
Classifier: Programming Language :: Python :: 3.10
Classifier: Programming Language :: Python :: 3.11
Classifier: Programming Language :: Python :: 3.12
Classifier: Operating System :: OS Independent
Requires-Python: >=3.10
License-File: LICENSE
Requires-Dist: GitPython>=3.1.0
Requires-Dist: click>=8.0.0
Requires-Dist: pydantic>=2.0.0
Requires-Dist: jinja2>=3.0.0
Requires-Dist: python-dateutil>=2.8.0
Requires-Dist: typing-extensions>=4.0.0; python_version < "3.11"
Provides-Extra: ai
Requires-Dist: anthropic>=0.25.0; extra == "ai"
Requires-Dist: openai>=1.0.0; extra == "ai"
Provides-Extra: mcp
Requires-Dist: mcp>=0.1.0; extra == "mcp"
Provides-Extra: dev
Requires-Dist: pytest>=7.0.0; extra == "dev"
Requires-Dist: pytest-cov>=4.0.0; extra == "dev"
Requires-Dist: black>=22.0.0; extra == "dev"
Requires-Dist: isort>=5.0.0; extra == "dev"
Requires-Dist: flake8>=4.0.0; extra == "dev"
Requires-Dist: mypy>=1.0.0; extra == "dev"
Requires-Dist: pre-commit>=3.0.0; extra == "dev"
Provides-Extra: docs
Requires-Dist: sphinx>=5.0.0; extra == "docs"
Requires-Dist: sphinx-rtd-theme>=1.0.0; extra == "docs"
Requires-Dist: myst-parser>=0.18.0; extra == "docs"
Dynamic: license-file
